[
      {
        "pbome": "Margherita",
        "price": 5.00
      },
      {
        "pizza_id": 2,
        "nome": "Marinara",
        "price": 4.50
      },
      {
        "pizza_id": 3,
        "nome": "Quattro Stagioni",
        "price": 7.50
      },
      {
        "pizza_id": 4,
        "nome": "Prosciutto e Funghi",
        "price": 6.50
      },
      {
        "pizza_id": 5,
        "nome": "Diavola",
        "price": 6.00
      },
      {
        "pizza_id": 6,
        "nome": "Capricciosa",
        "price": 7.00
      },
      {
        "pizza_id": 7,
        "nome": "Quattro Formaggi",
        "price": 8.00
      },
      {
        "pizza_id": 8,
        "nome": "Vegetariana",
        "price": 6.50
      },
      {
        "pizza_id": 9,
        "nome": "Hawaiian",
        "price": 7.00
      },
      {
        "pizza_id": 10,
        "nome": "Boscaiola",
        "price": 7.50
      }
    ]